src/better-pyxel/__init__.py
src/better-pyxel/better.py
src/better-pyxel/manager.py
src/better-pyxel/sprite.py
src/better-pyxel/tile.py
src/better-pyxel/vector.py
better_pyxel-0.0.1.dist-info/METADATA
better_pyxel-0.0.1.dist-info/WHEEL
better_pyxel-0.0.1.dist-info/licenses/LICENSE
better_pyxel-0.0.1.dist-info/RECORD
