Metadata-Version: 2.1
Name: better-pyxel
Version: 0.0.1
Summary: Making pyxel API usable
Author-email: Mattéo Leullier <pypi@8x13b.tk>
License-File: LICENSE
Classifier: Operating System :: OS Independent
Classifier: Programming Language :: Python :: 3
Requires-Python: >=3.7
